pysectprop/__init__.py
pysectprop/config.py
pysectprop/extruded/__init__.py
pysectprop/extruded/isection.py
pysectprop/extruded/jsection.py
pysectprop/extruded/lsection.py
pysectprop/extruded/omegasection.py
pysectprop/extruded/tsection.py
pysectprop/extruded/zsection.py
pysectprop/formed/__init__.py
pysectprop/formed/csectionformed.py
pysectprop/formed/lsectionformed.py
pysectprop/formed/omegasectionformed.py
pysectprop/formed/zsectionformed.py
pysectprop/general/__init__.py
pysectprop/general/arc.py
pysectprop/general/compositesection.py
pysectprop/general/cripplingsection.py
pysectprop/general/generalsection.py
pysectprop/general/hollowsection.py
pysectprop/general/line.py
pysectprop/general/material.py
pysectprop/general/materialsection.py
pysectprop/general/mould.py
pysectprop/general/numericalsection.py
pysectprop/general/point.py
pysectprop/general/sector.py
pysectprop/general/thinwalledsection.py
pysectprop/results/__init__.py
pysectprop/results/sectionresult.py
pysectprop/standard/__init__.py
pysectprop/standard/circlesection.py
pysectprop/standard/rectanglesection.py
pysectprop/standard/semitubesection.py
pysectprop/standard/squaresection.py
pysectprop/standard/tubesection.py
pysectprop-0.2.1.dist-info/licenses/LICENSE
pysectprop-0.2.1.dist-info/METADATA
pysectprop-0.2.1.dist-info/WHEEL
pysectprop-0.2.1.dist-info/top_level.txt
pysectprop-0.2.1.dist-info/RECORD
