Metadata-Version: 2.4
Name: pysectprop
Version: 0.2.1
Summary: Python Package for Section Properties
Author-email: Xero64 <xero64@gmail.com>
License-Expression: MIT
Project-URL: Homepage, https://github.com/Xero64/pysectprop
Project-URL: Issues, https://github.com/Xero64/pysectprop/issues
Classifier: Programming Language :: Python :: 3
Classifier: Operating System :: OS Independent
Requires-Python: >=3.10
License-File: LICENSE
Requires-Dist: matplotlib>=3.10.5
Requires-Dist: py2md>=0.1.3
Dynamic: license-file
